worker_client/__init__.py
worker_client/client.py
worker_client/types.py
mesh_sync_worker_backend_client-4.0.18.dist-info/METADATA
mesh_sync_worker_backend_client-4.0.18.dist-info/WHEEL
mesh_sync_worker_backend_client-4.0.18.dist-info/top_level.txt
mesh_sync_worker_backend_client-4.0.18.dist-info/RECORD
