Metadata-Version: 2.4
Name: mesh-sync-worker-backend-client
Version: 4.0.18
Summary: Auto-generated Python client for Mesh-Sync worker-backend
Home-page: https://github.com/Mesh-Sync/worker-backend
Author: Mesh-Sync
Author-email: 
License: ISC
Project-URL: Homepage, https://github.com/Mesh-Sync/worker-backend
Project-URL: Bug Reports, https://github.com/Mesh-Sync/worker-backend/issues
Project-URL: Source, https://github.com/Mesh-Sync/worker-backend
Keywords: worker,job-queue,bullmq,client,mesh-sync
Classifier: Development Status :: 4 - Beta
Classifier: Intended Audience :: Developers
Classifier: Programming Language :: Python :: 3
Classifier: Programming Language :: Python :: 3.8
Classifier: Programming Language :: Python :: 3.9
Classifier: Programming Language :: Python :: 3.10
Classifier: Programming Language :: Python :: 3.11
Classifier: Programming Language :: Python :: 3.12
Requires-Python: >=3.8
Requires-Dist: requests>=2.31.0
Dynamic: home-page
Dynamic: requires-python
